lsdb_rubin/__init__.py
lsdb_rubin/_version.py
lsdb_rubin/plot_light_curve.py
lsdb_rubin/tract_patch_search.py
lsdb_rubin/rsp_tests/README.md
lsdb_rubin/rsp_tests/__init__.py
lsdb_rubin/rsp_tests/critical_functions.py
lsdb_rubin/rsp_tests/random_access.py
lsdb_rubin-0.1.1.dist-info/licenses/LICENSE
lsdb_rubin-0.1.1.dist-info/METADATA
lsdb_rubin-0.1.1.dist-info/WHEEL
lsdb_rubin-0.1.1.dist-info/top_level.txt
lsdb_rubin-0.1.1.dist-info/RECORD
