Metadata-Version: 2.4
Name: lsdb_rubin
Version: 0.1.1
Author-email: LINCC Frameworks <lincc-frameworks-team@lists.lsst.org>
License-Expression: BSD-3-Clause
Project-URL: Source Code, https://github.com/astronomy-commons/lsdb_rubin
Classifier: Development Status :: 4 - Beta
Classifier: Intended Audience :: Developers
Classifier: Intended Audience :: Science/Research
Classifier: Operating System :: OS Independent
Classifier: Programming Language :: Python
Requires-Python: >=3.11
License-File: LICENSE
Requires-Dist: lsdb>=0.6.6
Requires-Dist: skymap-convert>=0.1.1
Provides-Extra: dev
Requires-Dist: asv[virtualenv]==0.6.5; extra == "dev"
Requires-Dist: jupyter; extra == "dev"
Requires-Dist: pre-commit; extra == "dev"
Requires-Dist: pytest; extra == "dev"
Requires-Dist: pytest-cov; extra == "dev"
Requires-Dist: ruff; extra == "dev"
Dynamic: license-file
